gisweb_tenants/__init__.py
gisweb_tenants/config.py
gisweb_tenants/crypto.py
gisweb_tenants/db.py
gisweb_tenants/exceptions.py
gisweb_tenants/registry.py
gisweb_tenants-0.1.11.dist-info/METADATA
gisweb_tenants-0.1.11.dist-info/WHEEL
gisweb_tenants-0.1.11.dist-info/RECORD
