Metadata-Version: 2.3
Name: gisweb-tenants
Version: 0.1.11
Summary: Gestione multi tenant
Author: Roberto Starnini
Author-email: roberto.starnini@gmail.com
Requires-Python: >=3.10,<3.13
Classifier: Programming Language :: Python :: 3
Classifier: Programming Language :: Python :: 3.10
Classifier: Programming Language :: Python :: 3.11
Classifier: Programming Language :: Python :: 3.12
Requires-Dist: PyYAML (>=6.0)
Requires-Dist: authlib[crypto] (>=1.6.3,<2.0.0)
Requires-Dist: bcrypt (>=4.1.1,<5.0.0)
Requires-Dist: cryptography (>=46.0.3,<47.0.0)
Requires-Dist: fastapi (>=0.95)
Requires-Dist: psycopg (>=3.1)
Requires-Dist: pyjwt[crypto] (>=2.8.0,<3.0.0)
Requires-Dist: sqlalchemy (>=2.0)
